oraicle/__init__.py
oraicle/autoagent.py
oraicle/context.py
oraicle/exceptions.py
oraicle/registry.py
oraicle/runtime.py
oraicle/tools.py
oraicle/adk/__init__.py
oraicle/adk/agent_wrapper.py
oraicle/adk/loader_patch.py
oraicle-2.0.0.dist-info/licenses/LICENSE
oraicle-2.0.0.dist-info/METADATA
oraicle-2.0.0.dist-info/WHEEL
oraicle-2.0.0.dist-info/top_level.txt
oraicle-2.0.0.dist-info/RECORD
