Metadata-Version: 2.4
Name: oraicle
Version: 2.0.0
Summary: Oraicle-Agent — Turn any Google-ADK Agent into a root_agent dynamically.
Author-email: Zack Mariano <zack.cmariano@oraicle.ai>
License: MIT License
Project-URL: Homepage, https://github.com/zackcmariano/oraicle-agent
Project-URL: Documentation, https://github.com/zackcmariano/oraicle-agent
Project-URL: Issues, https://github.com/zackcmariano/oraicle-agent/issues
Keywords: google-adk,agent,ai-agents,vertex-ai,multi-agent,a2a
Classifier: Development Status :: 3 - Alpha
Classifier: Intended Audience :: Developers
Classifier: License :: OSI Approved :: MIT License
Classifier: Programming Language :: Python :: 3
Classifier: Programming Language :: Python :: 3.10
Classifier: Programming Language :: Python :: 3.11
Classifier: Programming Language :: Python :: 3.12
Requires-Python: >=3.10
License-File: LICENSE
Requires-Dist: google-adk>=1.16.0
Dynamic: license-file
